aiosplinter/__init__.py
aiosplinter/__init__.pyi
aiosplinter-0.1.2.dist-info/LICENSE
aiosplinter-0.1.2.dist-info/WHEEL
aiosplinter-0.1.2.dist-info/METADATA
aiosplinter-0.1.2.dist-info/RECORD
