Metadata-Version: 2.1
Name: aiosplinter
Version: 0.1.2
Summary: Asynchronous splinter wrapper Python library
Home-page: https://github.com/rominf/aiosplinter
License: Apache-2.0
Keywords: splinter,web,browser,web-browser,automation,selenium,async,asyncio
Author: Roman Inflianskas
Author-email: infroma@gmail.com
Requires-Python: >=3.6,<4.0
Classifier: License :: OSI Approved :: Apache Software License
Classifier: Programming Language :: Python :: 3
Classifier: Programming Language :: Python :: 3.6
Classifier: Programming Language :: Python :: 3.7
Classifier: Topic :: Software Development :: Libraries :: Python Modules
Requires-Dist: aioify
Requires-Dist: poetry-version (>=0.1.2,<0.2.0)
Requires-Dist: splinter (>=0.9.0,<0.10.0)
Project-URL: Repository, https://github.com/rominf/aiosplinter
